grpug_poetry_demo/__init__.py
grpug_poetry_demo-0.1.0.dist-info/WHEEL
grpug_poetry_demo-0.1.0.dist-info/METADATA
grpug_poetry_demo-0.1.0.dist-info/RECORD
