Metadata-Version: 2.1
Name: grpug-poetry-demo
Version: 0.1.0
Summary: 
Author: Jace Browning
Author-email: jacebrowning@gmail.com
Requires-Python: >=3.4,<4.0
Classifier: Programming Language :: Python :: 3
Classifier: Programming Language :: Python :: 3.4
Classifier: Programming Language :: Python :: 3.5
Classifier: Programming Language :: Python :: 3.6
Classifier: Programming Language :: Python :: 3.7
Requires-Dist: django (>=2,<3)
